MANIFEST.in
setup.py
Risk.egg-info/PKG-INFO
Risk.egg-info/SOURCES.txt
Risk.egg-info/dependency_links.txt
Risk.egg-info/not-zip-safe
Risk.egg-info/top_level.txt
app/__init__.py
app/forms.py
app/models.py
risk/__init__.py
risk/board_graph.json
risk/game.py
risk/models.py
test/test_board.py
test/test_game.py