Metadata-Version: 1.1
Name: Risk
Version: 0.1.2
Summary: Objects and mthods for playing the boardgame Risk
Home-page: https://github.com/eriktaubeneck/hacker-risk
Author: Erik Taubeneck
Author-email: erik.taubeneck@gmail.com
License: UNKNOWN
Platform: any
Classifier: Environment :: Web Environment
Classifier: Intended Audience :: Developers
Classifier: Operating System :: OS Independent
Classifier: Programming Language :: Python
Classifier: Topic :: Software Development :: Libraries :: Python Modules
